evocloud_agent_toolkit/__init__.py
evocloud_agent_toolkit/linkpaymcp.py
evocloud_agent_toolkit/langchain/__init__.py
evocloud_agent_toolkit/langchain/linkpay_tool.py
evocloud_agent_toolkit/langchain/toolkit.py
evocloud_agent_toolkit-0.1.4.dist-info/licenses/LICENSE
evocloud_agent_toolkit-0.1.4.dist-info/METADATA
evocloud_agent_toolkit-0.1.4.dist-info/WHEEL
evocloud_agent_toolkit-0.1.4.dist-info/entry_points.txt
evocloud_agent_toolkit-0.1.4.dist-info/top_level.txt
evocloud_agent_toolkit-0.1.4.dist-info/RECORD
