Metadata-Version: 2.4
Name: evocloud-agent-toolkit
Version: 0.1.4
Summary: EvoCloud Agent Toolkit - Python SDK for AI-powered payment integration
Author-email: EvoCloud SDK Team <sdk@evocloud.com>
License: MIT
Project-URL: Homepage, https://github.com/evocloud/evocloud-agent-toolkit
Project-URL: Documentation, https://evocloud-agent-toolkit.readthedocs.io
Project-URL: Repository, https://github.com/evocloud/evocloud-agent-toolkit.git
Project-URL: Issues, https://github.com/evocloud/evocloud-agent-toolkit/issues
Keywords: evocloud,payment,ai,agent,toolkit,langchain,mcp
Classifier: Development Status :: 3 - Alpha
Classifier: Intended Audience :: Developers
Classifier: License :: OSI Approved :: MIT License
Classifier: Programming Language :: Python :: 3
Classifier: Programming Language :: Python :: 3.8
Classifier: Programming Language :: Python :: 3.9
Classifier: Programming Language :: Python :: 3.10
Classifier: Programming Language :: Python :: 3.11
Classifier: Programming Language :: Python :: 3.12
Classifier: Topic :: Software Development :: Libraries :: Python Modules
Classifier: Topic :: Office/Business :: Financial
Classifier: Topic :: Scientific/Engineering :: Artificial Intelligence
Requires-Python: >=3.8
License-File: LICENSE
Requires-Dist: evocloud-sdk>=0.1.1
Requires-Dist: langchain-core>=0.1.0
Requires-Dist: pydantic>=2.0.0
Requires-Dist: mcp[cli]>=0.1.0
Provides-Extra: dev
Requires-Dist: pytest>=6.0; extra == "dev"
Requires-Dist: pytest-cov>=2.0; extra == "dev"
Requires-Dist: black>=21.0; extra == "dev"
Requires-Dist: isort>=5.0; extra == "dev"
Requires-Dist: flake8>=3.8; extra == "dev"
Requires-Dist: mypy>=0.910; extra == "dev"
Provides-Extra: docs
Requires-Dist: sphinx>=4.0; extra == "docs"
Requires-Dist: sphinx-rtd-theme>=1.0; extra == "docs"
Requires-Dist: myst-parser>=0.15.0; extra == "docs"
Provides-Extra: examples
Requires-Dist: jupyter>=1.0; extra == "examples"
Requires-Dist: ipython>=7.0; extra == "examples"
Dynamic: license-file
